rabbitmq_admin/__init__.py
rabbitmq_admin/api.py
rabbitmq_admin/base.py
rabbitmq_admin/version.py
rabbitmq_admin/tests/__init__.py
rabbitmq_admin/tests/api_tests.py
rabbitmq_admin/tests/base_tests.py
rabbitmq_admin-0.2.dist-info/DESCRIPTION.rst
rabbitmq_admin-0.2.dist-info/METADATA
rabbitmq_admin-0.2.dist-info/metadata.json
rabbitmq_admin-0.2.dist-info/RECORD
rabbitmq_admin-0.2.dist-info/top_level.txt
rabbitmq_admin-0.2.dist-info/WHEEL
