Metadata-Version: 1.1
Name: rabbitmq-admin
Version: 0.2
Summary: A python interface for the RabbitMQ Admin HTTP API
Home-page: https://github.com/ambitioninc/rabbitmq-admin
Author: Micah Hausler
Author-email: opensource@ambition.com
License: MIT
Keywords: RabbitMQ,AMQP,admin
Platform: UNKNOWN
Classifier: Programming Language :: Python :: 2.7
Classifier: Programming Language :: Python :: 3.4
Classifier: Programming Language :: Python :: 3.5
Classifier: Intended Audience :: Developers
Classifier: License :: OSI Approved :: MIT License
Classifier: Operating System :: OS Independent
